AUTHORS
INSTALL
LICENSE
MANIFEST.in
README.rst
setup.py
timer3/__init__.py
timer3.egg-info/PKG-INFO
timer3.egg-info/SOURCES.txt
timer3.egg-info/dependency_links.txt
timer3.egg-info/not-zip-safe
timer3.egg-info/top_level.txt